swiftly/__init__.py
swiftly/core/__init__.py
swiftly/core/cli.py
swiftly/core/config.py
swiftly/core/main.py
swiftly/runtime/__init__.py
swiftly/runtime/python/__init__.py
swiftly/runtime/python/config.py
swiftly/runtime/python/main.py
swiftly/runtime/python/frameworks/__init__.py
swiftly/runtime/python/frameworks/django/__init__.py
swiftly/runtime/python/frameworks/django/config.py
swiftly/runtime/python/frameworks/django/main.py
swiftly/runtime/python/templates/gitignore.txt
swiftly/utils/__init__.py
swiftly/utils/check.py
swiftly/utils/cli.py
swiftly/utils/do.py
swiftly/utils/get.py
swiftly/utils/git.py
swiftly/utils/loader.py
swiftly/utils/template.py
swiftly_sys-0.0.121.data/scripts/swiftly
swiftly_sys-0.0.121.data/scripts/swiftly-python-django.bat
swiftly_sys-0.0.121.data/scripts/swiftly-python-django.sh
swiftly_sys-0.0.121.data/scripts/swiftly-python.bat
swiftly_sys-0.0.121.data/scripts/swiftly-python.sh
swiftly_sys-0.0.121.data/scripts/swiftly-utils.bat
swiftly_sys-0.0.121.data/scripts/swiftly-utils.sh
swiftly_sys-0.0.121.data/scripts/swiftly.bat
swiftly_sys-0.0.121.dist-info/LICENCE
swiftly_sys-0.0.121.dist-info/METADATA
swiftly_sys-0.0.121.dist-info/WHEEL
swiftly_sys-0.0.121.dist-info/top_level.txt
swiftly_sys-0.0.121.dist-info/RECORD
