Metadata-Version: 2.1
Name: swiftly-sys
Version: 0.0.121
Summary: Do what you're good at; writing code. Swiftly handle the rest
Home-page: https://github.com/brainspoof/swiftly-sys
Author: Shubham Gupta
Author-email: shubhastro2@gmail.com
License: Apache2
Keywords: python project,project management,code management,project building,python project managment,organized project
License-File: LICENCE
Requires-Dist: questionary
Requires-Dist: requests
Requires-Dist: pipdeptree
Requires-Dist: jinja2
